{
				"id": "user237",
				"title": "Arithmetic on the Frontier by Rudyard Kipling",
				"exclude_from_menu": "true",
				"image": "The U.S. Army 2.jpg",
				"tag": ["4", "28", "15"],
				"video": {
					"src": ["Explosion-on-black-2.m4v", "Explosion-on-black.m4v", "Explosion-on-black2.m4v", "Shooting-automatic-gun-on-backdrop-4.m4v","Shooting-automatic-gun-on-backdrop-4.m4v","Abandoned-car-on-fire.mp4","Slow-motion-rising-flames-closeup-2.m4v","Slow-motion-shooting-explosion.m4v","Slow-motion-strong-explosion.m4v","Car-burning-in-icy-lot-with-flames.m4v","Slow-motion-dark-ink-splatter-3.m4v","Slow-motion-dark-ink-splatter.m4v",  "Slow-motion-destroying-sheet-of-glass.m4v", "Slow-motion-dart-popping-water-balloon.m4v","Slow-motion-instant-explosion-2184.m4v","Slow-motion-smashing-alarm-clock-with-sledgehammer.m4v", "Slow-motion-smashing-tv-screen-with-sledgehammer.m4v","Slow-motion-dark-ink-splatter-3.m4v","Slow-motion-dark-ink-splatter.m4v","Slow-motion-dropping-and-breaking-piggy-bank.m4v", "Slow-motion-destroying-sheet-of-glass.m4v", "Slow-motion-dart-popping-water-balloon.m4v","Slow-motion-instant-explosion-2184.m4v","Slow-motion-smashing-alarm-clock-with-sledgehammer.m4v", "Slow-motion-smashing-tv-screen-with-sledgehammer.m4v"],
					"type": "background"	
				},
				"main_text": "A great and glorious thing it is<br>To learn, for seven years or so,<br>The Lord knows what of that and this,<br>Ere reckoned fit to face the foe --<br>The flying bullet down the Pass,<br>That whistles clear: 'All flesh is grass.'<br><br>Three hundred pounds per annum spent<br>On making brain and body meeter<br>For all the murderous intent<br>Comprised in 'villanous saltpetre!'<br>And after -- ask the Yusufzaies<br>What comes of all our 'ologies.<br><br>A scrimmage in a Border Station --<br>A canter down some dark defile --<br>Two thousand pounds of education<br>Drops to a ten-rupee jezail --<br>The Crammer's boast, the Squadron's pride,<br>Shot like a rabbit in a ride!<br><br>No proposition Euclid wrote,<br>No formulae the text-books know,<br>Will turn the bullet from your coat,<br>Or ward the tulwar's downward blow<br>Strike hard who cares -- shoot straight who can --<br>The odds are on the cheaper man.<br><br>One sword-knot stolen from the camp<br>Will pay for all the school expenses<br>Of any Kurrum Valley scamp<br>Who knows no word of moods and tenses,<br>But, being blessed with perfect sight,<br>Picks off our messmates left and right.<br><br>With home-bred hordes the hillsides teem,<br>The troop-ships bring us one by one,<br>At vast expense of time and steam,<br>To slay Afridis where they run.<br>The 'captives of our bow and spear'<br>Are cheap -- alas! as we are dear. "
			}